manparams/__init__.py
manparams/constants.py
manparams/edit.py
manparams/error.py
manparams/io.py
manparams/version.py
manparams-1.0.1.dist-info/AUTHORS.rst
manparams-1.0.1.dist-info/LICENSE
manparams-1.0.1.dist-info/METADATA
manparams-1.0.1.dist-info/WHEEL
manparams-1.0.1.dist-info/top_level.txt
manparams-1.0.1.dist-info/RECORD
