Metadata-Version: 2.1
Name: manparams
Version: 1.0.1
Summary: Management of parameters for simulations purposes
Home-page: https://gitlab.com/revesansparole/manparams
Author: revesansparole
Author-email: revesansparole@gmail.com
License: cc_by_nc
Platform: UNKNOWN
Classifier: Development Status :: 2 - Pre-Alpha
Classifier: Intended Audience :: Developers
Classifier: License :: OSI Approved :: BSD License
Classifier: Natural Language :: English
Classifier: Programming Language :: Python
Classifier: Programming Language :: Python :: 3
Classifier: Programming Language :: Python :: 3 :: Only
Classifier: Programming Language :: Python :: 3.7
Classifier: Programming Language :: Python :: 3.8
Classifier: Programming Language :: Python :: 3.9
Requires-Dist: marshmallow-dataclass
